MANIFEST.in
README.md
setup.cfg
setup.py
racengine/__init__.py
racengine/conf.json
racengine/demo.py
racengine/exceptions.py
racengine/main.py
racengine.egg-info/PKG-INFO
racengine.egg-info/SOURCES.txt
racengine.egg-info/dependency_links.txt
racengine.egg-info/requires.txt
racengine.egg-info/top_level.txt
racengine/converter/__init__.py
racengine/converter/converter.py
racengine/email_sender/SMTPServer.py
racengine/email_sender/__init__.py
racengine/email_sender/sender.py
racengine/templater/__init__.py
racengine/templater/renderer.py