Metadata-Version: 1.1
Name: racengine
Version: 0.1.24
Summary: Generate Docx from template (using external api endpoint) and convert it to PDF or another format(using external api endpoint)
Home-page: UNKNOWN
Author: SFERENO SAS
Author-email: adminsys@sfereno.com
License: UNKNOWN
Platform: UNKNOWN
Classifier: Development Status :: 5 - Production/Stable
Classifier: Intended Audience :: Developers
